python_oak_leaf_drawer/__init__.py
python_oak_leaf_drawer/oak.py
python_oak_leaf_drawer-1.0.3.dist-info/LICENSE
python_oak_leaf_drawer-1.0.3.dist-info/METADATA
python_oak_leaf_drawer-1.0.3.dist-info/WHEEL
python_oak_leaf_drawer-1.0.3.dist-info/top_level.txt
python_oak_leaf_drawer-1.0.3.dist-info/RECORD
